{
  "year": 2022,
  "months": [
    {
      "month": 1,
      "holidays": [
        {
          "date": "20220101",
          "name": "開國紀念日",
          "isHoliday": true,
          "isWeekend": true,
          "isSpecialHoliday": true,
          "description": "開國紀念日"
        },
        {
          "date": "20220102",
          "name": "",
          "isHoliday": true,
          "isWeekend": true,
          "isSpecialHoliday": false,
          "description": ""
        },
        {
          "date": "20220103",
          "name": "",
          "isHoliday": false,
          "isWeekend": false,
          "isSpecialHoliday": false,
          "description": ""
        },
        {
          "date": "20220104",
          "name": "",
          "isHoliday": false,
          "isWeekend": false,
          "isSpecialHoliday": false,
          "description": ""
        },
        {
          "date": "20220105",
          "name": "",
          "isHoliday": false,
          "isWeekend": false,
          "isSpecialHoliday": false,
          "description": ""
        },
        {
          "date": "20220106",
          "name": "",
          "isHoliday": false,
          "isWeekend": false,
          "isSpecialHoliday": false,
          "description": ""
        },
        {
          "date": "20220107",
          "name": "",
          "isHoliday": false,
          "isWeekend": false,
          "isSpecialHoliday": false,
          "description": ""
        },
        {
          "date": "20220108",
          "name": "",
          "isHoliday": true,
          "isWeekend": true,
          "isSpecialHoliday": false,
          "description": ""
        },
        {
          "date": "20220109",
          "name": "",
          "isHoliday": true,
          "isWeekend": true,
          "isSpecialHoliday": false,
          "description": ""
        },
        {
          "date": "20220110",
          "name": "",
          "isHoliday": false,
          "isWeekend": false,
          "isSpecialHoliday": false,
          "description": ""
        },
        {
          "date": "20220111",
          "name": "",
          "isHoliday": false,
          "isWeekend": false,
          "isSpecialHoliday": false,
          "description": ""
        },
        {
          "date": "20220112",
          "name": "",
          "isHoliday": false,
          "isWeekend": false,
          "isSpecialHoliday": false,
          "description": ""
        },
        {
          "date": "20220113",
          "name": "",
          "isHoliday": false,
          "isWeekend": false,
          "isSpecialHoliday": false,
          "description": ""
        },
        {
          "date": "20220114",
          "name": "",
          "isHoliday": false,
          "isWeekend": false,
          "isSpecialHoliday": false,
          "description": ""
        },
        {
          "date": "20220115",
          "name": "",
          "isHoliday": true,
          "isWeekend": true,
          "isSpecialHoliday": false,
          "description": ""
        },
        {
          "date": "20220116",
          "name": "",
          "isHoliday": true,
          "isWeekend": true,
          "isSpecialHoliday": false,
          "description": ""
        },
        {
          "date": "20220117",
          "name": "",
          "isHoliday": false,
          "isWeekend": false,
          "isSpecialHoliday": false,
          "description": ""
        },
        {
          "date": "20220118",
          "name": "",
          "isHoliday": false,
          "isWeekend": false,
          "isSpecialHoliday": false,
          "description": ""
        },
        {
          "date": "20220119",
          "name": "",
          "isHoliday": false,
          "isWeekend": false,
          "isSpecialHoliday": false,
          "description": ""
        },
        {
          "date": "20220120",
          "name": "",
          "isHoliday": false,
          "isWeekend": false,
          "isSpecialHoliday": false,
          "description": ""
        },
        {
          "date": "20220121",
          "name": "",
          "isHoliday": false,
          "isWeekend": false,
          "isSpecialHoliday": false,
          "description": ""
        },
        {
          "date": "20220122",
          "name": "補行上班",
          "isHoliday": false,
          "isWeekend": true,
          "isSpecialHoliday": false,
          "description": "補行上班"
        },
        {
          "date": "20220123",
          "name": "",
          "isHoliday": true,
          "isWeekend": true,
          "isSpecialHoliday": false,
          "description": ""
        },
        {
          "date": "20220124",
          "name": "",
          "isHoliday": false,
          "isWeekend": false,
          "isSpecialHoliday": false,
          "description": ""
        },
        {
          "date": "20220125",
          "name": "",
          "isHoliday": false,
          "isWeekend": false,
          "isSpecialHoliday": false,
          "description": ""
        },
        {
          "date": "20220126",
          "name": "",
          "isHoliday": false,
          "isWeekend": false,
          "isSpecialHoliday": false,
          "description": ""
        },
        {
          "date": "20220127",
          "name": "",
          "isHoliday": false,
          "isWeekend": false,
          "isSpecialHoliday": false,
          "description": ""
        },
        {
          "date": "20220128",
          "name": "",
          "isHoliday": false,
          "isWeekend": false,
          "isSpecialHoliday": false,
          "description": ""
        },
        {
          "date": "20220129",
          "name": "",
          "isHoliday": true,
          "isWeekend": true,
          "isSpecialHoliday": false,
          "description": ""
        },
        {
          "date": "20220130",
          "name": "",
          "isHoliday": true,
          "isWeekend": true,
          "isSpecialHoliday": false,
          "description": ""
        },
        {
          "date": "20220131",
          "name": "農曆除夕",
          "isHoliday": true,
          "isWeekend": false,
          "isSpecialHoliday": true,
          "description": "農曆除夕"
        }
      ]
    },
    {
      "month": 2,
      "holidays": [
        {
          "date": "20220201",
          "name": "春節",
          "isHoliday": true,
          "isWeekend": false,
          "isSpecialHoliday": true,
          "description": "春節"
        },
        {
          "date": "20220202",
          "name": "春節",
          "isHoliday": true,
          "isWeekend": false,
          "isSpecialHoliday": true,
          "description": "春節"
        },
        {
          "date": "20220203",
          "name": "春節",
          "isHoliday": true,
          "isWeekend": false,
          "isSpecialHoliday": true,
          "description": "春節"
        },
        {
          "date": "20220204",
          "name": "調整放假",
          "isHoliday": true,
          "isWeekend": false,
          "isSpecialHoliday": true,
          "description": "調整放假"
        },
        {
          "date": "20220205",
          "name": "",
          "isHoliday": true,
          "isWeekend": true,
          "isSpecialHoliday": false,
          "description": ""
        },
        {
          "date": "20220206",
          "name": "",
          "isHoliday": true,
          "isWeekend": true,
          "isSpecialHoliday": false,
          "description": ""
        },
        {
          "date": "20220207",
          "name": "",
          "isHoliday": false,
          "isWeekend": false,
          "isSpecialHoliday": false,
          "description": ""
        },
        {
          "date": "20220208",
          "name": "",
          "isHoliday": false,
          "isWeekend": false,
          "isSpecialHoliday": false,
          "description": ""
        },
        {
          "date": "20220209",
          "name": "",
          "isHoliday": false,
          "isWeekend": false,
          "isSpecialHoliday": false,
          "description": ""
        },
        {
          "date": "20220210",
          "name": "",
          "isHoliday": false,
          "isWeekend": false,
          "isSpecialHoliday": false,
          "description": ""
        },
        {
          "date": "20220211",
          "name": "",
          "isHoliday": false,
          "isWeekend": false,
          "isSpecialHoliday": false,
          "description": ""
        },
        {
          "date": "20220212",
          "name": "",
          "isHoliday": true,
          "isWeekend": true,
          "isSpecialHoliday": false,
          "description": ""
        },
        {
          "date": "20220213",
          "name": "",
          "isHoliday": true,
          "isWeekend": true,
          "isSpecialHoliday": false,
          "description": ""
        },
        {
          "date": "20220214",
          "name": "",
          "isHoliday": false,
          "isWeekend": false,
          "isSpecialHoliday": false,
          "description": ""
        },
        {
          "date": "20220215",
          "name": "",
          "isHoliday": false,
          "isWeekend": false,
          "isSpecialHoliday": false,
          "description": ""
        },
        {
          "date": "20220216",
          "name": "",
          "isHoliday": false,
          "isWeekend": false,
          "isSpecialHoliday": false,
          "description": ""
        },
        {
          "date": "20220217",
          "name": "",
          "isHoliday": false,
          "isWeekend": false,
          "isSpecialHoliday": false,
          "description": ""
        },
        {
          "date": "20220218",
          "name": "",
          "isHoliday": false,
          "isWeekend": false,
          "isSpecialHoliday": false,
          "description": ""
        },
        {
          "date": "20220219",
          "name": "",
          "isHoliday": true,
          "isWeekend": true,
          "isSpecialHoliday": false,
          "description": ""
        },
        {
          "date": "20220220",
          "name": "",
          "isHoliday": true,
          "isWeekend": true,
          "isSpecialHoliday": false,
          "description": ""
        },
        {
          "date": "20220221",
          "name": "",
          "isHoliday": false,
          "isWeekend": false,
          "isSpecialHoliday": false,
          "description": ""
        },
        {
          "date": "20220222",
          "name": "",
          "isHoliday": false,
          "isWeekend": false,
          "isSpecialHoliday": false,
          "description": ""
        },
        {
          "date": "20220223",
          "name": "",
          "isHoliday": false,
          "isWeekend": false,
          "isSpecialHoliday": false,
          "description": ""
        },
        {
          "date": "20220224",
          "name": "",
          "isHoliday": false,
          "isWeekend": false,
          "isSpecialHoliday": false,
          "description": ""
        },
        {
          "date": "20220225",
          "name": "",
          "isHoliday": false,
          "isWeekend": false,
          "isSpecialHoliday": false,
          "description": ""
        },
        {
          "date": "20220226",
          "name": "",
          "isHoliday": true,
          "isWeekend": true,
          "isSpecialHoliday": false,
          "description": ""
        },
        {
          "date": "20220227",
          "name": "",
          "isHoliday": true,
          "isWeekend": true,
          "isSpecialHoliday": false,
          "description": ""
        },
        {
          "date": "20220228",
          "name": "和平紀念日",
          "isHoliday": true,
          "isWeekend": false,
          "isSpecialHoliday": true,
          "description": "和平紀念日"
        }
      ]
    },
    {
      "month": 3,
      "holidays": [
        {
          "date": "20220301",
          "name": "",
          "isHoliday": false,
          "isWeekend": false,
          "isSpecialHoliday": false,
          "description": ""
        },
        {
          "date": "20220302",
          "name": "",
          "isHoliday": false,
          "isWeekend": false,
          "isSpecialHoliday": false,
          "description": ""
        },
        {
          "date": "20220303",
          "name": "",
          "isHoliday": false,
          "isWeekend": false,
          "isSpecialHoliday": false,
          "description": ""
        },
        {
          "date": "20220304",
          "name": "",
          "isHoliday": false,
          "isWeekend": false,
          "isSpecialHoliday": false,
          "description": ""
        },
        {
          "date": "20220305",
          "name": "",
          "isHoliday": true,
          "isWeekend": true,
          "isSpecialHoliday": false,
          "description": ""
        },
        {
          "date": "20220306",
          "name": "",
          "isHoliday": true,
          "isWeekend": true,
          "isSpecialHoliday": false,
          "description": ""
        },
        {
          "date": "20220307",
          "name": "",
          "isHoliday": false,
          "isWeekend": false,
          "isSpecialHoliday": false,
          "description": ""
        },
        {
          "date": "20220308",
          "name": "",
          "isHoliday": false,
          "isWeekend": false,
          "isSpecialHoliday": false,
          "description": ""
        },
        {
          "date": "20220309",
          "name": "",
          "isHoliday": false,
          "isWeekend": false,
          "isSpecialHoliday": false,
          "description": ""
        },
        {
          "date": "20220310",
          "name": "",
          "isHoliday": false,
          "isWeekend": false,
          "isSpecialHoliday": false,
          "description": ""
        },
        {
          "date": "20220311",
          "name": "",
          "isHoliday": false,
          "isWeekend": false,
          "isSpecialHoliday": false,
          "description": ""
        },
        {
          "date": "20220312",
          "name": "",
          "isHoliday": true,
          "isWeekend": true,
          "isSpecialHoliday": false,
          "description": ""
        },
        {
          "date": "20220313",
          "name": "",
          "isHoliday": true,
          "isWeekend": true,
          "isSpecialHoliday": false,
          "description": ""
        },
        {
          "date": "20220314",
          "name": "",
          "isHoliday": false,
          "isWeekend": false,
          "isSpecialHoliday": false,
          "description": ""
        },
        {
          "date": "20220315",
          "name": "",
          "isHoliday": false,
          "isWeekend": false,
          "isSpecialHoliday": false,
          "description": ""
        },
        {
          "date": "20220316",
          "name": "",
          "isHoliday": false,
          "isWeekend": false,
          "isSpecialHoliday": false,
          "description": ""
        },
        {
          "date": "20220317",
          "name": "",
          "isHoliday": false,
          "isWeekend": false,
          "isSpecialHoliday": false,
          "description": ""
        },
        {
          "date": "20220318",
          "name": "",
          "isHoliday": false,
          "isWeekend": false,
          "isSpecialHoliday": false,
          "description": ""
        },
        {
          "date": "20220319",
          "name": "",
          "isHoliday": true,
          "isWeekend": true,
          "isSpecialHoliday": false,
          "description": ""
        },
        {
          "date": "20220320",
          "name": "",
          "isHoliday": true,
          "isWeekend": true,
          "isSpecialHoliday": false,
          "description": ""
        },
        {
          "date": "20220321",
          "name": "",
          "isHoliday": false,
          "isWeekend": false,
          "isSpecialHoliday": false,
          "description": ""
        },
        {
          "date": "20220322",
          "name": "",
          "isHoliday": false,
          "isWeekend": false,
          "isSpecialHoliday": false,
          "description": ""
        },
        {
          "date": "20220323",
          "name": "",
          "isHoliday": false,
          "isWeekend": false,
          "isSpecialHoliday": false,
          "description": ""
        },
        {
          "date": "20220324",
          "name": "",
          "isHoliday": false,
          "isWeekend": false,
          "isSpecialHoliday": false,
          "description": ""
        },
        {
          "date": "20220325",
          "name": "",
          "isHoliday": false,
          "isWeekend": false,
          "isSpecialHoliday": false,
          "description": ""
        },
        {
          "date": "20220326",
          "name": "",
          "isHoliday": true,
          "isWeekend": true,
          "isSpecialHoliday": false,
          "description": ""
        },
        {
          "date": "20220327",
          "name": "",
          "isHoliday": true,
          "isWeekend": true,
          "isSpecialHoliday": false,
          "description": ""
        },
        {
          "date": "20220328",
          "name": "",
          "isHoliday": false,
          "isWeekend": false,
          "isSpecialHoliday": false,
          "description": ""
        },
        {
          "date": "20220329",
          "name": "",
          "isHoliday": false,
          "isWeekend": false,
          "isSpecialHoliday": false,
          "description": ""
        },
        {
          "date": "20220330",
          "name": "",
          "isHoliday": false,
          "isWeekend": false,
          "isSpecialHoliday": false,
          "description": ""
        },
        {
          "date": "20220331",
          "name": "",
          "isHoliday": false,
          "isWeekend": false,
          "isSpecialHoliday": false,
          "description": ""
        }
      ]
    },
    {
      "month": 4,
      "holidays": [
        {
          "date": "20220401",
          "name": "",
          "isHoliday": false,
          "isWeekend": false,
          "isSpecialHoliday": false,
          "description": ""
        },
        {
          "date": "20220402",
          "name": "",
          "isHoliday": true,
          "isWeekend": true,
          "isSpecialHoliday": false,
          "description": ""
        },
        {
          "date": "20220403",
          "name": "",
          "isHoliday": true,
          "isWeekend": true,
          "isSpecialHoliday": false,
          "description": ""
        },
        {
          "date": "20220404",
          "name": "兒童節",
          "isHoliday": true,
          "isWeekend": false,
          "isSpecialHoliday": true,
          "description": "兒童節"
        },
        {
          "date": "20220405",
          "name": "民族掃墓節",
          "isHoliday": true,
          "isWeekend": false,
          "isSpecialHoliday": true,
          "description": "民族掃墓節"
        },
        {
          "date": "20220406",
          "name": "",
          "isHoliday": false,
          "isWeekend": false,
          "isSpecialHoliday": false,
          "description": ""
        },
        {
          "date": "20220407",
          "name": "",
          "isHoliday": false,
          "isWeekend": false,
          "isSpecialHoliday": false,
          "description": ""
        },
        {
          "date": "20220408",
          "name": "",
          "isHoliday": false,
          "isWeekend": false,
          "isSpecialHoliday": false,
          "description": ""
        },
        {
          "date": "20220409",
          "name": "",
          "isHoliday": true,
          "isWeekend": true,
          "isSpecialHoliday": false,
          "description": ""
        },
        {
          "date": "20220410",
          "name": "",
          "isHoliday": true,
          "isWeekend": true,
          "isSpecialHoliday": false,
          "description": ""
        },
        {
          "date": "20220411",
          "name": "",
          "isHoliday": false,
          "isWeekend": false,
          "isSpecialHoliday": false,
          "description": ""
        },
        {
          "date": "20220412",
          "name": "",
          "isHoliday": false,
          "isWeekend": false,
          "isSpecialHoliday": false,
          "description": ""
        },
        {
          "date": "20220413",
          "name": "",
          "isHoliday": false,
          "isWeekend": false,
          "isSpecialHoliday": false,
          "description": ""
        },
        {
          "date": "20220414",
          "name": "",
          "isHoliday": false,
          "isWeekend": false,
          "isSpecialHoliday": false,
          "description": ""
        },
        {
          "date": "20220415",
          "name": "",
          "isHoliday": false,
          "isWeekend": false,
          "isSpecialHoliday": false,
          "description": ""
        },
        {
          "date": "20220416",
          "name": "",
          "isHoliday": true,
          "isWeekend": true,
          "isSpecialHoliday": false,
          "description": ""
        },
        {
          "date": "20220417",
          "name": "",
          "isHoliday": true,
          "isWeekend": true,
          "isSpecialHoliday": false,
          "description": ""
        },
        {
          "date": "20220418",
          "name": "",
          "isHoliday": false,
          "isWeekend": false,
          "isSpecialHoliday": false,
          "description": ""
        },
        {
          "date": "20220419",
          "name": "",
          "isHoliday": false,
          "isWeekend": false,
          "isSpecialHoliday": false,
          "description": ""
        },
        {
          "date": "20220420",
          "name": "",
          "isHoliday": false,
          "isWeekend": false,
          "isSpecialHoliday": false,
          "description": ""
        },
        {
          "date": "20220421",
          "name": "",
          "isHoliday": false,
          "isWeekend": false,
          "isSpecialHoliday": false,
          "description": ""
        },
        {
          "date": "20220422",
          "name": "",
          "isHoliday": false,
          "isWeekend": false,
          "isSpecialHoliday": false,
          "description": ""
        },
        {
          "date": "20220423",
          "name": "",
          "isHoliday": true,
          "isWeekend": true,
          "isSpecialHoliday": false,
          "description": ""
        },
        {
          "date": "20220424",
          "name": "",
          "isHoliday": true,
          "isWeekend": true,
          "isSpecialHoliday": false,
          "description": ""
        },
        {
          "date": "20220425",
          "name": "",
          "isHoliday": false,
          "isWeekend": false,
          "isSpecialHoliday": false,
          "description": ""
        },
        {
          "date": "20220426",
          "name": "",
          "isHoliday": false,
          "isWeekend": false,
          "isSpecialHoliday": false,
          "description": ""
        },
        {
          "date": "20220427",
          "name": "",
          "isHoliday": false,
          "isWeekend": false,
          "isSpecialHoliday": false,
          "description": ""
        },
        {
          "date": "20220428",
          "name": "",
          "isHoliday": false,
          "isWeekend": false,
          "isSpecialHoliday": false,
          "description": ""
        },
        {
          "date": "20220429",
          "name": "",
          "isHoliday": false,
          "isWeekend": false,
          "isSpecialHoliday": false,
          "description": ""
        },
        {
          "date": "20220430",
          "name": "",
          "isHoliday": true,
          "isWeekend": true,
          "isSpecialHoliday": false,
          "description": ""
        }
      ]
    },
    {
      "month": 5,
      "holidays": [
        {
          "date": "20220501",
          "name": "",
          "isHoliday": true,
          "isWeekend": true,
          "isSpecialHoliday": false,
          "description": ""
        },
        {
          "date": "20220502",
          "name": "",
          "isHoliday": false,
          "isWeekend": false,
          "isSpecialHoliday": false,
          "description": ""
        },
        {
          "date": "20220503",
          "name": "",
          "isHoliday": false,
          "isWeekend": false,
          "isSpecialHoliday": false,
          "description": ""
        },
        {
          "date": "20220504",
          "name": "",
          "isHoliday": false,
          "isWeekend": false,
          "isSpecialHoliday": false,
          "description": ""
        },
        {
          "date": "20220505",
          "name": "",
          "isHoliday": false,
          "isWeekend": false,
          "isSpecialHoliday": false,
          "description": ""
        },
        {
          "date": "20220506",
          "name": "",
          "isHoliday": false,
          "isWeekend": false,
          "isSpecialHoliday": false,
          "description": ""
        },
        {
          "date": "20220507",
          "name": "",
          "isHoliday": true,
          "isWeekend": true,
          "isSpecialHoliday": false,
          "description": ""
        },
        {
          "date": "20220508",
          "name": "",
          "isHoliday": true,
          "isWeekend": true,
          "isSpecialHoliday": false,
          "description": ""
        },
        {
          "date": "20220509",
          "name": "",
          "isHoliday": false,
          "isWeekend": false,
          "isSpecialHoliday": false,
          "description": ""
        },
        {
          "date": "20220510",
          "name": "",
          "isHoliday": false,
          "isWeekend": false,
          "isSpecialHoliday": false,
          "description": ""
        },
        {
          "date": "20220511",
          "name": "",
          "isHoliday": false,
          "isWeekend": false,
          "isSpecialHoliday": false,
          "description": ""
        },
        {
          "date": "20220512",
          "name": "",
          "isHoliday": false,
          "isWeekend": false,
          "isSpecialHoliday": false,
          "description": ""
        },
        {
          "date": "20220513",
          "name": "",
          "isHoliday": false,
          "isWeekend": false,
          "isSpecialHoliday": false,
          "description": ""
        },
        {
          "date": "20220514",
          "name": "",
          "isHoliday": true,
          "isWeekend": true,
          "isSpecialHoliday": false,
          "description": ""
        },
        {
          "date": "20220515",
          "name": "",
          "isHoliday": true,
          "isWeekend": true,
          "isSpecialHoliday": false,
          "description": ""
        },
        {
          "date": "20220516",
          "name": "",
          "isHoliday": false,
          "isWeekend": false,
          "isSpecialHoliday": false,
          "description": ""
        },
        {
          "date": "20220517",
          "name": "",
          "isHoliday": false,
          "isWeekend": false,
          "isSpecialHoliday": false,
          "description": ""
        },
        {
          "date": "20220518",
          "name": "",
          "isHoliday": false,
          "isWeekend": false,
          "isSpecialHoliday": false,
          "description": ""
        },
        {
          "date": "20220519",
          "name": "",
          "isHoliday": false,
          "isWeekend": false,
          "isSpecialHoliday": false,
          "description": ""
        },
        {
          "date": "20220520",
          "name": "",
          "isHoliday": false,
          "isWeekend": false,
          "isSpecialHoliday": false,
          "description": ""
        },
        {
          "date": "20220521",
          "name": "",
          "isHoliday": true,
          "isWeekend": true,
          "isSpecialHoliday": false,
          "description": ""
        },
        {
          "date": "20220522",
          "name": "",
          "isHoliday": true,
          "isWeekend": true,
          "isSpecialHoliday": false,
          "description": ""
        },
        {
          "date": "20220523",
          "name": "",
          "isHoliday": false,
          "isWeekend": false,
          "isSpecialHoliday": false,
          "description": ""
        },
        {
          "date": "20220524",
          "name": "",
          "isHoliday": false,
          "isWeekend": false,
          "isSpecialHoliday": false,
          "description": ""
        },
        {
          "date": "20220525",
          "name": "",
          "isHoliday": false,
          "isWeekend": false,
          "isSpecialHoliday": false,
          "description": ""
        },
        {
          "date": "20220526",
          "name": "",
          "isHoliday": false,
          "isWeekend": false,
          "isSpecialHoliday": false,
          "description": ""
        },
        {
          "date": "20220527",
          "name": "",
          "isHoliday": false,
          "isWeekend": false,
          "isSpecialHoliday": false,
          "description": ""
        },
        {
          "date": "20220528",
          "name": "",
          "isHoliday": true,
          "isWeekend": true,
          "isSpecialHoliday": false,
          "description": ""
        },
        {
          "date": "20220529",
          "name": "",
          "isHoliday": true,
          "isWeekend": true,
          "isSpecialHoliday": false,
          "description": ""
        },
        {
          "date": "20220530",
          "name": "",
          "isHoliday": false,
          "isWeekend": false,
          "isSpecialHoliday": false,
          "description": ""
        },
        {
          "date": "20220531",
          "name": "",
          "isHoliday": false,
          "isWeekend": false,
          "isSpecialHoliday": false,
          "description": ""
        }
      ]
    },
    {
      "month": 6,
      "holidays": [
        {
          "date": "20220601",
          "name": "",
          "isHoliday": false,
          "isWeekend": false,
          "isSpecialHoliday": false,
          "description": ""
        },
        {
          "date": "20220602",
          "name": "",
          "isHoliday": false,
          "isWeekend": false,
          "isSpecialHoliday": false,
          "description": ""
        },
        {
          "date": "20220603",
          "name": "端午節",
          "isHoliday": true,
          "isWeekend": false,
          "isSpecialHoliday": true,
          "description": "端午節"
        },
        {
          "date": "20220604",
          "name": "",
          "isHoliday": true,
          "isWeekend": true,
          "isSpecialHoliday": false,
          "description": ""
        },
        {
          "date": "20220605",
          "name": "",
          "isHoliday": true,
          "isWeekend": true,
          "isSpecialHoliday": false,
          "description": ""
        },
        {
          "date": "20220606",
          "name": "",
          "isHoliday": false,
          "isWeekend": false,
          "isSpecialHoliday": false,
          "description": ""
        },
        {
          "date": "20220607",
          "name": "",
          "isHoliday": false,
          "isWeekend": false,
          "isSpecialHoliday": false,
          "description": ""
        },
        {
          "date": "20220608",
          "name": "",
          "isHoliday": false,
          "isWeekend": false,
          "isSpecialHoliday": false,
          "description": ""
        },
        {
          "date": "20220609",
          "name": "",
          "isHoliday": false,
          "isWeekend": false,
          "isSpecialHoliday": false,
          "description": ""
        },
        {
          "date": "20220610",
          "name": "",
          "isHoliday": false,
          "isWeekend": false,
          "isSpecialHoliday": false,
          "description": ""
        },
        {
          "date": "20220611",
          "name": "",
          "isHoliday": true,
          "isWeekend": true,
          "isSpecialHoliday": false,
          "description": ""
        },
        {
          "date": "20220612",
          "name": "",
          "isHoliday": true,
          "isWeekend": true,
          "isSpecialHoliday": false,
          "description": ""
        },
        {
          "date": "20220613",
          "name": "",
          "isHoliday": false,
          "isWeekend": false,
          "isSpecialHoliday": false,
          "description": ""
        },
        {
          "date": "20220614",
          "name": "",
          "isHoliday": false,
          "isWeekend": false,
          "isSpecialHoliday": false,
          "description": ""
        },
        {
          "date": "20220615",
          "name": "",
          "isHoliday": false,
          "isWeekend": false,
          "isSpecialHoliday": false,
          "description": ""
        },
        {
          "date": "20220616",
          "name": "",
          "isHoliday": false,
          "isWeekend": false,
          "isSpecialHoliday": false,
          "description": ""
        },
        {
          "date": "20220617",
          "name": "",
          "isHoliday": false,
          "isWeekend": false,
          "isSpecialHoliday": false,
          "description": ""
        },
        {
          "date": "20220618",
          "name": "",
          "isHoliday": true,
          "isWeekend": true,
          "isSpecialHoliday": false,
          "description": ""
        },
        {
          "date": "20220619",
          "name": "",
          "isHoliday": true,
          "isWeekend": true,
          "isSpecialHoliday": false,
          "description": ""
        },
        {
          "date": "20220620",
          "name": "",
          "isHoliday": false,
          "isWeekend": false,
          "isSpecialHoliday": false,
          "description": ""
        },
        {
          "date": "20220621",
          "name": "",
          "isHoliday": false,
          "isWeekend": false,
          "isSpecialHoliday": false,
          "description": ""
        },
        {
          "date": "20220622",
          "name": "",
          "isHoliday": false,
          "isWeekend": false,
          "isSpecialHoliday": false,
          "description": ""
        },
        {
          "date": "20220623",
          "name": "",
          "isHoliday": false,
          "isWeekend": false,
          "isSpecialHoliday": false,
          "description": ""
        },
        {
          "date": "20220624",
          "name": "",
          "isHoliday": false,
          "isWeekend": false,
          "isSpecialHoliday": false,
          "description": ""
        },
        {
          "date": "20220625",
          "name": "",
          "isHoliday": true,
          "isWeekend": true,
          "isSpecialHoliday": false,
          "description": ""
        },
        {
          "date": "20220626",
          "name": "",
          "isHoliday": true,
          "isWeekend": true,
          "isSpecialHoliday": false,
          "description": ""
        },
        {
          "date": "20220627",
          "name": "",
          "isHoliday": false,
          "isWeekend": false,
          "isSpecialHoliday": false,
          "description": ""
        },
        {
          "date": "20220628",
          "name": "",
          "isHoliday": false,
          "isWeekend": false,
          "isSpecialHoliday": false,
          "description": ""
        },
        {
          "date": "20220629",
          "name": "",
          "isHoliday": false,
          "isWeekend": false,
          "isSpecialHoliday": false,
          "description": ""
        },
        {
          "date": "20220630",
          "name": "",
          "isHoliday": false,
          "isWeekend": false,
          "isSpecialHoliday": false,
          "description": ""
        }
      ]
    },
    {
      "month": 7,
      "holidays": [
        {
          "date": "20220701",
          "name": "",
          "isHoliday": false,
          "isWeekend": false,
          "isSpecialHoliday": false,
          "description": ""
        },
        {
          "date": "20220702",
          "name": "",
          "isHoliday": true,
          "isWeekend": true,
          "isSpecialHoliday": false,
          "description": ""
        },
        {
          "date": "20220703",
          "name": "",
          "isHoliday": true,
          "isWeekend": true,
          "isSpecialHoliday": false,
          "description": ""
        },
        {
          "date": "20220704",
          "name": "",
          "isHoliday": false,
          "isWeekend": false,
          "isSpecialHoliday": false,
          "description": ""
        },
        {
          "date": "20220705",
          "name": "",
          "isHoliday": false,
          "isWeekend": false,
          "isSpecialHoliday": false,
          "description": ""
        },
        {
          "date": "20220706",
          "name": "",
          "isHoliday": false,
          "isWeekend": false,
          "isSpecialHoliday": false,
          "description": ""
        },
        {
          "date": "20220707",
          "name": "",
          "isHoliday": false,
          "isWeekend": false,
          "isSpecialHoliday": false,
          "description": ""
        },
        {
          "date": "20220708",
          "name": "",
          "isHoliday": false,
          "isWeekend": false,
          "isSpecialHoliday": false,
          "description": ""
        },
        {
          "date": "20220709",
          "name": "",
          "isHoliday": true,
          "isWeekend": true,
          "isSpecialHoliday": false,
          "description": ""
        },
        {
          "date": "20220710",
          "name": "",
          "isHoliday": true,
          "isWeekend": true,
          "isSpecialHoliday": false,
          "description": ""
        },
        {
          "date": "20220711",
          "name": "",
          "isHoliday": false,
          "isWeekend": false,
          "isSpecialHoliday": false,
          "description": ""
        },
        {
          "date": "20220712",
          "name": "",
          "isHoliday": false,
          "isWeekend": false,
          "isSpecialHoliday": false,
          "description": ""
        },
        {
          "date": "20220713",
          "name": "",
          "isHoliday": false,
          "isWeekend": false,
          "isSpecialHoliday": false,
          "description": ""
        },
        {
          "date": "20220714",
          "name": "",
          "isHoliday": false,
          "isWeekend": false,
          "isSpecialHoliday": false,
          "description": ""
        },
        {
          "date": "20220715",
          "name": "",
          "isHoliday": false,
          "isWeekend": false,
          "isSpecialHoliday": false,
          "description": ""
        },
        {
          "date": "20220716",
          "name": "",
          "isHoliday": true,
          "isWeekend": true,
          "isSpecialHoliday": false,
          "description": ""
        },
        {
          "date": "20220717",
          "name": "",
          "isHoliday": true,
          "isWeekend": true,
          "isSpecialHoliday": false,
          "description": ""
        },
        {
          "date": "20220718",
          "name": "",
          "isHoliday": false,
          "isWeekend": false,
          "isSpecialHoliday": false,
          "description": ""
        },
        {
          "date": "20220719",
          "name": "",
          "isHoliday": false,
          "isWeekend": false,
          "isSpecialHoliday": false,
          "description": ""
        },
        {
          "date": "20220720",
          "name": "",
          "isHoliday": false,
          "isWeekend": false,
          "isSpecialHoliday": false,
          "description": ""
        },
        {
          "date": "20220721",
          "name": "",
          "isHoliday": false,
          "isWeekend": false,
          "isSpecialHoliday": false,
          "description": ""
        },
        {
          "date": "20220722",
          "name": "",
          "isHoliday": false,
          "isWeekend": false,
          "isSpecialHoliday": false,
          "description": ""
        },
        {
          "date": "20220723",
          "name": "",
          "isHoliday": true,
          "isWeekend": true,
          "isSpecialHoliday": false,
          "description": ""
        },
        {
          "date": "20220724",
          "name": "",
          "isHoliday": true,
          "isWeekend": true,
          "isSpecialHoliday": false,
          "description": ""
        },
        {
          "date": "20220725",
          "name": "",
          "isHoliday": false,
          "isWeekend": false,
          "isSpecialHoliday": false,
          "description": ""
        },
        {
          "date": "20220726",
          "name": "",
          "isHoliday": false,
          "isWeekend": false,
          "isSpecialHoliday": false,
          "description": ""
        },
        {
          "date": "20220727",
          "name": "",
          "isHoliday": false,
          "isWeekend": false,
          "isSpecialHoliday": false,
          "description": ""
        },
        {
          "date": "20220728",
          "name": "",
          "isHoliday": false,
          "isWeekend": false,
          "isSpecialHoliday": false,
          "description": ""
        },
        {
          "date": "20220729",
          "name": "",
          "isHoliday": false,
          "isWeekend": false,
          "isSpecialHoliday": false,
          "description": ""
        },
        {
          "date": "20220730",
          "name": "",
          "isHoliday": true,
          "isWeekend": true,
          "isSpecialHoliday": false,
          "description": ""
        },
        {
          "date": "20220731",
          "name": "",
          "isHoliday": true,
          "isWeekend": true,
          "isSpecialHoliday": false,
          "description": ""
        }
      ]
    },
    {
      "month": 8,
      "holidays": [
        {
          "date": "20220801",
          "name": "",
          "isHoliday": false,
          "isWeekend": false,
          "isSpecialHoliday": false,
          "description": ""
        },
        {
          "date": "20220802",
          "name": "",
          "isHoliday": false,
          "isWeekend": false,
          "isSpecialHoliday": false,
          "description": ""
        },
        {
          "date": "20220803",
          "name": "",
          "isHoliday": false,
          "isWeekend": false,
          "isSpecialHoliday": false,
          "description": ""
        },
        {
          "date": "20220804",
          "name": "",
          "isHoliday": false,
          "isWeekend": false,
          "isSpecialHoliday": false,
          "description": ""
        },
        {
          "date": "20220805",
          "name": "",
          "isHoliday": false,
          "isWeekend": false,
          "isSpecialHoliday": false,
          "description": ""
        },
        {
          "date": "20220806",
          "name": "",
          "isHoliday": true,
          "isWeekend": true,
          "isSpecialHoliday": false,
          "description": ""
        },
        {
          "date": "20220807",
          "name": "",
          "isHoliday": true,
          "isWeekend": true,
          "isSpecialHoliday": false,
          "description": ""
        },
        {
          "date": "20220808",
          "name": "",
          "isHoliday": false,
          "isWeekend": false,
          "isSpecialHoliday": false,
          "description": ""
        },
        {
          "date": "20220809",
          "name": "",
          "isHoliday": false,
          "isWeekend": false,
          "isSpecialHoliday": false,
          "description": ""
        },
        {
          "date": "20220810",
          "name": "",
          "isHoliday": false,
          "isWeekend": false,
          "isSpecialHoliday": false,
          "description": ""
        },
        {
          "date": "20220811",
          "name": "",
          "isHoliday": false,
          "isWeekend": false,
          "isSpecialHoliday": false,
          "description": ""
        },
        {
          "date": "20220812",
          "name": "",
          "isHoliday": false,
          "isWeekend": false,
          "isSpecialHoliday": false,
          "description": ""
        },
        {
          "date": "20220813",
          "name": "",
          "isHoliday": true,
          "isWeekend": true,
          "isSpecialHoliday": false,
          "description": ""
        },
        {
          "date": "20220814",
          "name": "",
          "isHoliday": true,
          "isWeekend": true,
          "isSpecialHoliday": false,
          "description": ""
        },
        {
          "date": "20220815",
          "name": "",
          "isHoliday": false,
          "isWeekend": false,
          "isSpecialHoliday": false,
          "description": ""
        },
        {
          "date": "20220816",
          "name": "",
          "isHoliday": false,
          "isWeekend": false,
          "isSpecialHoliday": false,
          "description": ""
        },
        {
          "date": "20220817",
          "name": "",
          "isHoliday": false,
          "isWeekend": false,
          "isSpecialHoliday": false,
          "description": ""
        },
        {
          "date": "20220818",
          "name": "",
          "isHoliday": false,
          "isWeekend": false,
          "isSpecialHoliday": false,
          "description": ""
        },
        {
          "date": "20220819",
          "name": "",
          "isHoliday": false,
          "isWeekend": false,
          "isSpecialHoliday": false,
          "description": ""
        },
        {
          "date": "20220820",
          "name": "",
          "isHoliday": true,
          "isWeekend": true,
          "isSpecialHoliday": false,
          "description": ""
        },
        {
          "date": "20220821",
          "name": "",
          "isHoliday": true,
          "isWeekend": true,
          "isSpecialHoliday": false,
          "description": ""
        },
        {
          "date": "20220822",
          "name": "",
          "isHoliday": false,
          "isWeekend": false,
          "isSpecialHoliday": false,
          "description": ""
        },
        {
          "date": "20220823",
          "name": "",
          "isHoliday": false,
          "isWeekend": false,
          "isSpecialHoliday": false,
          "description": ""
        },
        {
          "date": "20220824",
          "name": "",
          "isHoliday": false,
          "isWeekend": false,
          "isSpecialHoliday": false,
          "description": ""
        },
        {
          "date": "20220825",
          "name": "",
          "isHoliday": false,
          "isWeekend": false,
          "isSpecialHoliday": false,
          "description": ""
        },
        {
          "date": "20220826",
          "name": "",
          "isHoliday": false,
          "isWeekend": false,
          "isSpecialHoliday": false,
          "description": ""
        },
        {
          "date": "20220827",
          "name": "",
          "isHoliday": true,
          "isWeekend": true,
          "isSpecialHoliday": false,
          "description": ""
        },
        {
          "date": "20220828",
          "name": "",
          "isHoliday": true,
          "isWeekend": true,
          "isSpecialHoliday": false,
          "description": ""
        },
        {
          "date": "20220829",
          "name": "",
          "isHoliday": false,
          "isWeekend": false,
          "isSpecialHoliday": false,
          "description": ""
        },
        {
          "date": "20220830",
          "name": "",
          "isHoliday": false,
          "isWeekend": false,
          "isSpecialHoliday": false,
          "description": ""
        },
        {
          "date": "20220831",
          "name": "",
          "isHoliday": false,
          "isWeekend": false,
          "isSpecialHoliday": false,
          "description": ""
        }
      ]
    },
    {
      "month": 9,
      "holidays": [
        {
          "date": "20220901",
          "name": "",
          "isHoliday": false,
          "isWeekend": false,
          "isSpecialHoliday": false,
          "description": ""
        },
        {
          "date": "20220902",
          "name": "",
          "isHoliday": false,
          "isWeekend": false,
          "isSpecialHoliday": false,
          "description": ""
        },
        {
          "date": "20220903",
          "name": "",
          "isHoliday": true,
          "isWeekend": true,
          "isSpecialHoliday": false,
          "description": ""
        },
        {
          "date": "20220904",
          "name": "",
          "isHoliday": true,
          "isWeekend": true,
          "isSpecialHoliday": false,
          "description": ""
        },
        {
          "date": "20220905",
          "name": "",
          "isHoliday": false,
          "isWeekend": false,
          "isSpecialHoliday": false,
          "description": ""
        },
        {
          "date": "20220906",
          "name": "",
          "isHoliday": false,
          "isWeekend": false,
          "isSpecialHoliday": false,
          "description": ""
        },
        {
          "date": "20220907",
          "name": "",
          "isHoliday": false,
          "isWeekend": false,
          "isSpecialHoliday": false,
          "description": ""
        },
        {
          "date": "20220908",
          "name": "",
          "isHoliday": false,
          "isWeekend": false,
          "isSpecialHoliday": false,
          "description": ""
        },
        {
          "date": "20220909",
          "name": "補假",
          "isHoliday": true,
          "isWeekend": false,
          "isSpecialHoliday": true,
          "description": "補假"
        },
        {
          "date": "20220910",
          "name": "中秋節",
          "isHoliday": true,
          "isWeekend": true,
          "isSpecialHoliday": true,
          "description": "中秋節"
        },
        {
          "date": "20220911",
          "name": "",
          "isHoliday": true,
          "isWeekend": true,
          "isSpecialHoliday": false,
          "description": ""
        },
        {
          "date": "20220912",
          "name": "",
          "isHoliday": false,
          "isWeekend": false,
          "isSpecialHoliday": false,
          "description": ""
        },
        {
          "date": "20220913",
          "name": "",
          "isHoliday": false,
          "isWeekend": false,
          "isSpecialHoliday": false,
          "description": ""
        },
        {
          "date": "20220914",
          "name": "",
          "isHoliday": false,
          "isWeekend": false,
          "isSpecialHoliday": false,
          "description": ""
        },
        {
          "date": "20220915",
          "name": "",
          "isHoliday": false,
          "isWeekend": false,
          "isSpecialHoliday": false,
          "description": ""
        },
        {
          "date": "20220916",
          "name": "",
          "isHoliday": false,
          "isWeekend": false,
          "isSpecialHoliday": false,
          "description": ""
        },
        {
          "date": "20220917",
          "name": "",
          "isHoliday": true,
          "isWeekend": true,
          "isSpecialHoliday": false,
          "description": ""
        },
        {
          "date": "20220918",
          "name": "",
          "isHoliday": true,
          "isWeekend": true,
          "isSpecialHoliday": false,
          "description": ""
        },
        {
          "date": "20220919",
          "name": "",
          "isHoliday": false,
          "isWeekend": false,
          "isSpecialHoliday": false,
          "description": ""
        },
        {
          "date": "20220920",
          "name": "",
          "isHoliday": false,
          "isWeekend": false,
          "isSpecialHoliday": false,
          "description": ""
        },
        {
          "date": "20220921",
          "name": "",
          "isHoliday": false,
          "isWeekend": false,
          "isSpecialHoliday": false,
          "description": ""
        },
        {
          "date": "20220922",
          "name": "",
          "isHoliday": false,
          "isWeekend": false,
          "isSpecialHoliday": false,
          "description": ""
        },
        {
          "date": "20220923",
          "name": "",
          "isHoliday": false,
          "isWeekend": false,
          "isSpecialHoliday": false,
          "description": ""
        },
        {
          "date": "20220924",
          "name": "",
          "isHoliday": true,
          "isWeekend": true,
          "isSpecialHoliday": false,
          "description": ""
        },
        {
          "date": "20220925",
          "name": "",
          "isHoliday": true,
          "isWeekend": true,
          "isSpecialHoliday": false,
          "description": ""
        },
        {
          "date": "20220926",
          "name": "",
          "isHoliday": false,
          "isWeekend": false,
          "isSpecialHoliday": false,
          "description": ""
        },
        {
          "date": "20220927",
          "name": "",
          "isHoliday": false,
          "isWeekend": false,
          "isSpecialHoliday": false,
          "description": ""
        },
        {
          "date": "20220928",
          "name": "",
          "isHoliday": false,
          "isWeekend": false,
          "isSpecialHoliday": false,
          "description": ""
        },
        {
          "date": "20220929",
          "name": "",
          "isHoliday": false,
          "isWeekend": false,
          "isSpecialHoliday": false,
          "description": ""
        },
        {
          "date": "20220930",
          "name": "",
          "isHoliday": false,
          "isWeekend": false,
          "isSpecialHoliday": false,
          "description": ""
        }
      ]
    },
    {
      "month": 10,
      "holidays": [
        {
          "date": "20221001",
          "name": "",
          "isHoliday": true,
          "isWeekend": true,
          "isSpecialHoliday": false,
          "description": ""
        },
        {
          "date": "20221002",
          "name": "",
          "isHoliday": true,
          "isWeekend": true,
          "isSpecialHoliday": false,
          "description": ""
        },
        {
          "date": "20221003",
          "name": "",
          "isHoliday": false,
          "isWeekend": false,
          "isSpecialHoliday": false,
          "description": ""
        },
        {
          "date": "20221004",
          "name": "",
          "isHoliday": false,
          "isWeekend": false,
          "isSpecialHoliday": false,
          "description": ""
        },
        {
          "date": "20221005",
          "name": "",
          "isHoliday": false,
          "isWeekend": false,
          "isSpecialHoliday": false,
          "description": ""
        },
        {
          "date": "20221006",
          "name": "",
          "isHoliday": false,
          "isWeekend": false,
          "isSpecialHoliday": false,
          "description": ""
        },
        {
          "date": "20221007",
          "name": "",
          "isHoliday": false,
          "isWeekend": false,
          "isSpecialHoliday": false,
          "description": ""
        },
        {
          "date": "20221008",
          "name": "",
          "isHoliday": true,
          "isWeekend": true,
          "isSpecialHoliday": false,
          "description": ""
        },
        {
          "date": "20221009",
          "name": "",
          "isHoliday": true,
          "isWeekend": true,
          "isSpecialHoliday": false,
          "description": ""
        },
        {
          "date": "20221010",
          "name": "國慶日",
          "isHoliday": true,
          "isWeekend": false,
          "isSpecialHoliday": true,
          "description": "國慶日"
        },
        {
          "date": "20221011",
          "name": "",
          "isHoliday": false,
          "isWeekend": false,
          "isSpecialHoliday": false,
          "description": ""
        },
        {
          "date": "20221012",
          "name": "",
          "isHoliday": false,
          "isWeekend": false,
          "isSpecialHoliday": false,
          "description": ""
        },
        {
          "date": "20221013",
          "name": "",
          "isHoliday": false,
          "isWeekend": false,
          "isSpecialHoliday": false,
          "description": ""
        },
        {
          "date": "20221014",
          "name": "",
          "isHoliday": false,
          "isWeekend": false,
          "isSpecialHoliday": false,
          "description": ""
        },
        {
          "date": "20221015",
          "name": "",
          "isHoliday": true,
          "isWeekend": true,
          "isSpecialHoliday": false,
          "description": ""
        },
        {
          "date": "20221016",
          "name": "",
          "isHoliday": true,
          "isWeekend": true,
          "isSpecialHoliday": false,
          "description": ""
        },
        {
          "date": "20221017",
          "name": "",
          "isHoliday": false,
          "isWeekend": false,
          "isSpecialHoliday": false,
          "description": ""
        },
        {
          "date": "20221018",
          "name": "",
          "isHoliday": false,
          "isWeekend": false,
          "isSpecialHoliday": false,
          "description": ""
        },
        {
          "date": "20221019",
          "name": "",
          "isHoliday": false,
          "isWeekend": false,
          "isSpecialHoliday": false,
          "description": ""
        },
        {
          "date": "20221020",
          "name": "",
          "isHoliday": false,
          "isWeekend": false,
          "isSpecialHoliday": false,
          "description": ""
        },
        {
          "date": "20221021",
          "name": "",
          "isHoliday": false,
          "isWeekend": false,
          "isSpecialHoliday": false,
          "description": ""
        },
        {
          "date": "20221022",
          "name": "",
          "isHoliday": true,
          "isWeekend": true,
          "isSpecialHoliday": false,
          "description": ""
        },
        {
          "date": "20221023",
          "name": "",
          "isHoliday": true,
          "isWeekend": true,
          "isSpecialHoliday": false,
          "description": ""
        },
        {
          "date": "20221024",
          "name": "",
          "isHoliday": false,
          "isWeekend": false,
          "isSpecialHoliday": false,
          "description": ""
        },
        {
          "date": "20221025",
          "name": "",
          "isHoliday": false,
          "isWeekend": false,
          "isSpecialHoliday": false,
          "description": ""
        },
        {
          "date": "20221026",
          "name": "",
          "isHoliday": false,
          "isWeekend": false,
          "isSpecialHoliday": false,
          "description": ""
        },
        {
          "date": "20221027",
          "name": "",
          "isHoliday": false,
          "isWeekend": false,
          "isSpecialHoliday": false,
          "description": ""
        },
        {
          "date": "20221028",
          "name": "",
          "isHoliday": false,
          "isWeekend": false,
          "isSpecialHoliday": false,
          "description": ""
        },
        {
          "date": "20221029",
          "name": "",
          "isHoliday": true,
          "isWeekend": true,
          "isSpecialHoliday": false,
          "description": ""
        },
        {
          "date": "20221030",
          "name": "",
          "isHoliday": true,
          "isWeekend": true,
          "isSpecialHoliday": false,
          "description": ""
        },
        {
          "date": "20221031",
          "name": "",
          "isHoliday": false,
          "isWeekend": false,
          "isSpecialHoliday": false,
          "description": ""
        }
      ]
    },
    {
      "month": 11,
      "holidays": [
        {
          "date": "20221101",
          "name": "",
          "isHoliday": false,
          "isWeekend": false,
          "isSpecialHoliday": false,
          "description": ""
        },
        {
          "date": "20221102",
          "name": "",
          "isHoliday": false,
          "isWeekend": false,
          "isSpecialHoliday": false,
          "description": ""
        },
        {
          "date": "20221103",
          "name": "",
          "isHoliday": false,
          "isWeekend": false,
          "isSpecialHoliday": false,
          "description": ""
        },
        {
          "date": "20221104",
          "name": "",
          "isHoliday": false,
          "isWeekend": false,
          "isSpecialHoliday": false,
          "description": ""
        },
        {
          "date": "20221105",
          "name": "",
          "isHoliday": true,
          "isWeekend": true,
          "isSpecialHoliday": false,
          "description": ""
        },
        {
          "date": "20221106",
          "name": "",
          "isHoliday": true,
          "isWeekend": true,
          "isSpecialHoliday": false,
          "description": ""
        },
        {
          "date": "20221107",
          "name": "",
          "isHoliday": false,
          "isWeekend": false,
          "isSpecialHoliday": false,
          "description": ""
        },
        {
          "date": "20221108",
          "name": "",
          "isHoliday": false,
          "isWeekend": false,
          "isSpecialHoliday": false,
          "description": ""
        },
        {
          "date": "20221109",
          "name": "",
          "isHoliday": false,
          "isWeekend": false,
          "isSpecialHoliday": false,
          "description": ""
        },
        {
          "date": "20221110",
          "name": "",
          "isHoliday": false,
          "isWeekend": false,
          "isSpecialHoliday": false,
          "description": ""
        },
        {
          "date": "20221111",
          "name": "",
          "isHoliday": false,
          "isWeekend": false,
          "isSpecialHoliday": false,
          "description": ""
        },
        {
          "date": "20221112",
          "name": "",
          "isHoliday": true,
          "isWeekend": true,
          "isSpecialHoliday": false,
          "description": ""
        },
        {
          "date": "20221113",
          "name": "",
          "isHoliday": true,
          "isWeekend": true,
          "isSpecialHoliday": false,
          "description": ""
        },
        {
          "date": "20221114",
          "name": "",
          "isHoliday": false,
          "isWeekend": false,
          "isSpecialHoliday": false,
          "description": ""
        },
        {
          "date": "20221115",
          "name": "",
          "isHoliday": false,
          "isWeekend": false,
          "isSpecialHoliday": false,
          "description": ""
        },
        {
          "date": "20221116",
          "name": "",
          "isHoliday": false,
          "isWeekend": false,
          "isSpecialHoliday": false,
          "description": ""
        },
        {
          "date": "20221117",
          "name": "",
          "isHoliday": false,
          "isWeekend": false,
          "isSpecialHoliday": false,
          "description": ""
        },
        {
          "date": "20221118",
          "name": "",
          "isHoliday": false,
          "isWeekend": false,
          "isSpecialHoliday": false,
          "description": ""
        },
        {
          "date": "20221119",
          "name": "",
          "isHoliday": true,
          "isWeekend": true,
          "isSpecialHoliday": false,
          "description": ""
        },
        {
          "date": "20221120",
          "name": "",
          "isHoliday": true,
          "isWeekend": true,
          "isSpecialHoliday": false,
          "description": ""
        },
        {
          "date": "20221121",
          "name": "",
          "isHoliday": false,
          "isWeekend": false,
          "isSpecialHoliday": false,
          "description": ""
        },
        {
          "date": "20221122",
          "name": "",
          "isHoliday": false,
          "isWeekend": false,
          "isSpecialHoliday": false,
          "description": ""
        },
        {
          "date": "20221123",
          "name": "",
          "isHoliday": false,
          "isWeekend": false,
          "isSpecialHoliday": false,
          "description": ""
        },
        {
          "date": "20221124",
          "name": "",
          "isHoliday": false,
          "isWeekend": false,
          "isSpecialHoliday": false,
          "description": ""
        },
        {
          "date": "20221125",
          "name": "",
          "isHoliday": false,
          "isWeekend": false,
          "isSpecialHoliday": false,
          "description": ""
        },
        {
          "date": "20221126",
          "name": "",
          "isHoliday": true,
          "isWeekend": true,
          "isSpecialHoliday": false,
          "description": ""
        },
        {
          "date": "20221127",
          "name": "",
          "isHoliday": true,
          "isWeekend": true,
          "isSpecialHoliday": false,
          "description": ""
        },
        {
          "date": "20221128",
          "name": "",
          "isHoliday": false,
          "isWeekend": false,
          "isSpecialHoliday": false,
          "description": ""
        },
        {
          "date": "20221129",
          "name": "",
          "isHoliday": false,
          "isWeekend": false,
          "isSpecialHoliday": false,
          "description": ""
        },
        {
          "date": "20221130",
          "name": "",
          "isHoliday": false,
          "isWeekend": false,
          "isSpecialHoliday": false,
          "description": ""
        }
      ]
    },
    {
      "month": 12,
      "holidays": [
        {
          "date": "20221201",
          "name": "",
          "isHoliday": false,
          "isWeekend": false,
          "isSpecialHoliday": false,
          "description": ""
        },
        {
          "date": "20221202",
          "name": "",
          "isHoliday": false,
          "isWeekend": false,
          "isSpecialHoliday": false,
          "description": ""
        },
        {
          "date": "20221203",
          "name": "",
          "isHoliday": true,
          "isWeekend": true,
          "isSpecialHoliday": false,
          "description": ""
        },
        {
          "date": "20221204",
          "name": "",
          "isHoliday": true,
          "isWeekend": true,
          "isSpecialHoliday": false,
          "description": ""
        },
        {
          "date": "20221205",
          "name": "",
          "isHoliday": false,
          "isWeekend": false,
          "isSpecialHoliday": false,
          "description": ""
        },
        {
          "date": "20221206",
          "name": "",
          "isHoliday": false,
          "isWeekend": false,
          "isSpecialHoliday": false,
          "description": ""
        },
        {
          "date": "20221207",
          "name": "",
          "isHoliday": false,
          "isWeekend": false,
          "isSpecialHoliday": false,
          "description": ""
        },
        {
          "date": "20221208",
          "name": "",
          "isHoliday": false,
          "isWeekend": false,
          "isSpecialHoliday": false,
          "description": ""
        },
        {
          "date": "20221209",
          "name": "",
          "isHoliday": false,
          "isWeekend": false,
          "isSpecialHoliday": false,
          "description": ""
        },
        {
          "date": "20221210",
          "name": "",
          "isHoliday": true,
          "isWeekend": true,
          "isSpecialHoliday": false,
          "description": ""
        },
        {
          "date": "20221211",
          "name": "",
          "isHoliday": true,
          "isWeekend": true,
          "isSpecialHoliday": false,
          "description": ""
        },
        {
          "date": "20221212",
          "name": "",
          "isHoliday": false,
          "isWeekend": false,
          "isSpecialHoliday": false,
          "description": ""
        },
        {
          "date": "20221213",
          "name": "",
          "isHoliday": false,
          "isWeekend": false,
          "isSpecialHoliday": false,
          "description": ""
        },
        {
          "date": "20221214",
          "name": "",
          "isHoliday": false,
          "isWeekend": false,
          "isSpecialHoliday": false,
          "description": ""
        },
        {
          "date": "20221215",
          "name": "",
          "isHoliday": false,
          "isWeekend": false,
          "isSpecialHoliday": false,
          "description": ""
        },
        {
          "date": "20221216",
          "name": "",
          "isHoliday": false,
          "isWeekend": false,
          "isSpecialHoliday": false,
          "description": ""
        },
        {
          "date": "20221217",
          "name": "",
          "isHoliday": true,
          "isWeekend": true,
          "isSpecialHoliday": false,
          "description": ""
        },
        {
          "date": "20221218",
          "name": "",
          "isHoliday": true,
          "isWeekend": true,
          "isSpecialHoliday": false,
          "description": ""
        },
        {
          "date": "20221219",
          "name": "",
          "isHoliday": false,
          "isWeekend": false,
          "isSpecialHoliday": false,
          "description": ""
        },
        {
          "date": "20221220",
          "name": "",
          "isHoliday": false,
          "isWeekend": false,
          "isSpecialHoliday": false,
          "description": ""
        },
        {
          "date": "20221221",
          "name": "",
          "isHoliday": false,
          "isWeekend": false,
          "isSpecialHoliday": false,
          "description": ""
        },
        {
          "date": "20221222",
          "name": "",
          "isHoliday": false,
          "isWeekend": false,
          "isSpecialHoliday": false,
          "description": ""
        },
        {
          "date": "20221223",
          "name": "",
          "isHoliday": false,
          "isWeekend": false,
          "isSpecialHoliday": false,
          "description": ""
        },
        {
          "date": "20221224",
          "name": "",
          "isHoliday": true,
          "isWeekend": true,
          "isSpecialHoliday": false,
          "description": ""
        },
        {
          "date": "20221225",
          "name": "",
          "isHoliday": true,
          "isWeekend": true,
          "isSpecialHoliday": false,
          "description": ""
        },
        {
          "date": "20221226",
          "name": "",
          "isHoliday": false,
          "isWeekend": false,
          "isSpecialHoliday": false,
          "description": ""
        },
        {
          "date": "20221227",
          "name": "",
          "isHoliday": false,
          "isWeekend": false,
          "isSpecialHoliday": false,
          "description": ""
        },
        {
          "date": "20221228",
          "name": "",
          "isHoliday": false,
          "isWeekend": false,
          "isSpecialHoliday": false,
          "description": ""
        },
        {
          "date": "20221229",
          "name": "",
          "isHoliday": false,
          "isWeekend": false,
          "isSpecialHoliday": false,
          "description": ""
        },
        {
          "date": "20221230",
          "name": "",
          "isHoliday": false,
          "isWeekend": false,
          "isSpecialHoliday": false,
          "description": ""
        },
        {
          "date": "20221231",
          "name": "",
          "isHoliday": true,
          "isWeekend": true,
          "isSpecialHoliday": false,
          "description": ""
        }
      ]
    }
  ],
  "generatedAt": "2025-10-13T09:56:35.409Z",
  "license": {
    "name": "政府資料開放授權條款",
    "url": "https://data.gov.tw/license",
    "attribution": "資料來源：行政院人事行政總處"
  }
}